pyrest_model_client/__init__.py
pyrest_model_client/base.py
pyrest_model_client/client.py
pyrest_model_client-0.0.3.dist-info/licenses/LICENSE
pyrest_model_client-0.0.3.dist-info/METADATA
pyrest_model_client-0.0.3.dist-info/WHEEL
pyrest_model_client-0.0.3.dist-info/top_level.txt
pyrest_model_client-0.0.3.dist-info/RECORD
