Metadata-Version: 2.4
Name: pyrest-model-client
Version: 0.0.3
Summary: A simple, flexible Python HTTP client and API modeling toolkit built on httpx and pydantic.
Home-page: https://github.com/aviz92/pyrest-model-client
Author: Avi Zaguri
Author-email: 
Project-URL: Repository, https://github.com/aviz92/pyrest-model-client
Requires-Python: >=3.11
License-File: LICENSE
Requires-Dist: setuptools
Requires-Dist: python-dotenv
Requires-Dist: pre-commit
Requires-Dist: wheel
Requires-Dist: colorlog
Requires-Dist: pytest
Requires-Dist: pathlib
Requires-Dist: httpx
Requires-Dist: pydantic
Requires-Dist: email-validator
Requires-Dist: pytest-mock
Requires-Dist: PyYAML
Requires-Dist: custom-python-logger
Requires-Dist: pytest-plugins
Requires-Dist: python-simple-email-sender
Requires-Dist: python-vault
Dynamic: author
Dynamic: description
Dynamic: description-content-type
Dynamic: home-page
Dynamic: license-file
Dynamic: project-url
Dynamic: requires-dist
Dynamic: requires-python
Dynamic: summary
